debug_toolbar_user_panel/__init__.py
debug_toolbar_user_panel/decorators.py
debug_toolbar_user_panel/forms.py
debug_toolbar_user_panel/models.py
debug_toolbar_user_panel/panels.py
debug_toolbar_user_panel/views.py
debug_toolbar_user_panel/templates/debug_toolbar_user_panel/panel.html
django_debug_toolbar_user_panel-2.0.0.dist-info/COPYING
django_debug_toolbar_user_panel-2.0.0.dist-info/METADATA
django_debug_toolbar_user_panel-2.0.0.dist-info/WHEEL
django_debug_toolbar_user_panel-2.0.0.dist-info/top_level.txt
django_debug_toolbar_user_panel-2.0.0.dist-info/RECORD
