Metadata-Version: 2.1
Name: django-debug-toolbar-user-panel
Version: 2.0.0
Summary: Panel for the Django Debug toolbar to quickly switch between users.
Home-page: https://chris-lamb.co.uk/projects/django-debug-toolbar-user-panel
Author: Chris Lamb
Author-email: chris@chris-lamb.co.uk
License: BSD
License-File: COPYING
